bullinv_quant_sdk/__init__.py
bullinv_quant_sdk/quote.py
bullinv_quant_sdk-0.1.7.dist-info/METADATA
bullinv_quant_sdk-0.1.7.dist-info/WHEEL
bullinv_quant_sdk-0.1.7.dist-info/top_level.txt
bullinv_quant_sdk-0.1.7.dist-info/RECORD
