Metadata-Version: 2.4
Name: bullinv_quant_sdk
Version: 0.1.7
Summary: Add your description here
Requires-Python: >=3.10
Requires-Dist: clickhouse-driver>=0.2.9
Requires-Dist: pandas>=2.2.3
Requires-Dist: python-dotenv>=1.0.1
